graiax_sayamod_jx3game_qiyu/__init__.py
graiax_sayamod_jx3game_qiyu/builtins/loop_manager.py
graiax_sayamod_jx3game_qiyu/static/qiyu.sql
graiax_sayamod_jx3game_qiyu/tables.py
graiax_sayamod_jx3game_qiyu-0.1.0.dist-info/WHEEL
graiax_sayamod_jx3game_qiyu-0.1.0.dist-info/METADATA
graiax_sayamod_jx3game_qiyu-0.1.0.dist-info/RECORD
